cmo/__init__.py
cmo/indicator/__init__.py
cmo/indicator/accumulative_icmop.py
cmo/indicator/erd.py
cmo/indicator/icmop.py
cmo/indicator/postprocessor.py
cmo/indicator/runtime_callback.py
cmo/problems/__init__.py
cmo/problems/cdtlz.py
cmo/problems/cf.py
cmo/problems/classic.py
cmo/problems/cre.py
cmo/problems/ctp.py
cmo/problems/dascmop.py
cmo/problems/dcdtlz.py
cmo/problems/doc.py
cmo/problems/factory.py
cmo/problems/lircmop.py
cmo/problems/modact.py
cmo/problems/mw.py
cmo/problems/nctp.py
cmo/problems/rcm.py
cmo/problems/step.py
cmo/problems/utils.py
cmo/problems/zxhcf.py
cmo/problems/pf/CDTLZ/c1-dtlz1_M2_D10.pf
cmo/problems/pf/CDTLZ/c1-dtlz1_M2_D2.pf
cmo/problems/pf/CDTLZ/c1-dtlz1_M2_D3.pf
cmo/problems/pf/CDTLZ/c1-dtlz1_M2_D30.pf
cmo/problems/pf/CDTLZ/c1-dtlz1_M2_D5.pf
cmo/problems/pf/CDTLZ/c1-dtlz1_M3_D10.pf
cmo/problems/pf/CDTLZ/c1-dtlz1_M3_D3.pf
cmo/problems/pf/CDTLZ/c1-dtlz1_M3_D30.pf
cmo/problems/pf/CDTLZ/c1-dtlz1_M3_D5.pf
cmo/problems/pf/CDTLZ/c1-dtlz3_M2_D10.pf
cmo/problems/pf/CDTLZ/c1-dtlz3_M2_D2.pf
cmo/problems/pf/CDTLZ/c1-dtlz3_M2_D3.pf
cmo/problems/pf/CDTLZ/c1-dtlz3_M2_D30.pf
cmo/problems/pf/CDTLZ/c1-dtlz3_M2_D5.pf
cmo/problems/pf/CDTLZ/c1-dtlz3_M3_D10.pf
cmo/problems/pf/CDTLZ/c1-dtlz3_M3_D3.pf
cmo/problems/pf/CDTLZ/c1-dtlz3_M3_D30.pf
cmo/problems/pf/CDTLZ/c1-dtlz3_M3_D5.pf
cmo/problems/pf/CDTLZ/c2-dtlz2_M2_D10.pf
cmo/problems/pf/CDTLZ/c2-dtlz2_M2_D2.pf
cmo/problems/pf/CDTLZ/c2-dtlz2_M2_D3.pf
cmo/problems/pf/CDTLZ/c2-dtlz2_M2_D30.pf
cmo/problems/pf/CDTLZ/c2-dtlz2_M2_D5.pf
cmo/problems/pf/CDTLZ/c2-dtlz2_M3_D10.pf
cmo/problems/pf/CDTLZ/c2-dtlz2_M3_D3.pf
cmo/problems/pf/CDTLZ/c2-dtlz2_M3_D30.pf
cmo/problems/pf/CDTLZ/c2-dtlz2_M3_D5.pf
cmo/problems/pf/CDTLZ/c3-dtlz1_M2_D10.pf
cmo/problems/pf/CDTLZ/c3-dtlz1_M2_D2.pf
cmo/problems/pf/CDTLZ/c3-dtlz1_M2_D3.pf
cmo/problems/pf/CDTLZ/c3-dtlz1_M2_D30.pf
cmo/problems/pf/CDTLZ/c3-dtlz1_M2_D5.pf
cmo/problems/pf/CDTLZ/c3-dtlz1_M3_D10.pf
cmo/problems/pf/CDTLZ/c3-dtlz1_M3_D3.pf
cmo/problems/pf/CDTLZ/c3-dtlz1_M3_D30.pf
cmo-0.1.8.dist-info/LICENSE
cmo-0.1.8.dist-info/METADATA
cmo-0.1.8.dist-info/WHEEL
cmo-0.1.8.dist-info/top_level.txt
cmo-0.1.8.dist-info/RECORD
